numer/__init__.py
numer/cmath.py
numer/gmp.dylib
numer/lib.dylib
numer/mpz.py
numer-0.0.141.dist-info/METADATA
numer-0.0.141.dist-info/WHEEL
numer-0.0.141.dist-info/top_level.txt
numer-0.0.141.dist-info/RECORD
